{"lede":"A look at January 18 through the almanac — historic events, famous birthdays including Sophia Reid-Gantzert and Zeeko Zaki, and the day's notable deaths and observances.","events":[{"year":2026,"title":"2026 Adamuz rail disaster","desc":"At least 45 people are killed and 292 others injured after two trains collide in Adamuz in the worst railway disaster in over a decade in Spain.","tag":"Crash of trains on"},{"year":2019,"title":"Tlahuelilpan pipeline explosion","desc":"An oil pipeline explosion near Tlahuelilpan, Hidalgo, Mexico, kills 137 people.","tag":"2019 gasoline pipeline explosion"},{"year":2002,"title":"Sierra Leone Civil War","desc":"The Sierra Leone Civil War is declared over.","tag":"1991–2002 war in West"},{"year":1983,"title":"International Olympic Committee","desc":"The International Olympic Committee restores Jim Thorpe's Olympic medals to his family.","tag":"Governing body of Olympic"},{"year":1976,"title":"Christianity in Lebanon","desc":"Lebanese Christian militias kill at least 1,000 in Karantina, Beirut.","tag":"History"},{"year":1958,"title":"Willie O'Ree","desc":"Willie O'Ree, the first Black Canadian National Hockey League player, makes his NHL debut with the Boston Bruins.","tag":"Canadian ice hockey player"},{"year":1941,"title":"World War II","desc":"World War II: British troops launch a general counter-offensive against Italian East Africa.","tag":"1939–1945 global conflict"},{"year":1919,"title":"World War I","desc":"World War I: The Paris Peace Conference opens in Versailles, France.","tag":"1914–1918 global conflict"},{"year":1788,"title":"First Fleet","desc":"The first elements of the First Fleet carrying 736 convicts from Great Britain to Australia arrive at Botany Bay.","tag":"11 British ships establishing"},{"year":474,"title":"Leo II (emperor)","desc":"Seven-year-old Leo II succeeds his maternal grandfather Leo I as Byzantine emperor. He dies ten months later.","tag":"Eastern Roman emperor in"}],"births":[{"monogram":"S","name":"Sophia Reid-Gantzert","year":2010,"line":"Canadian actress and dancer"},{"monogram":"Z","name":"Zeeko Zaki","year":1990,"line":"Egyptian-American actor"},{"monogram":"O","name":"Olivier Rochus","year":1981,"line":"Belgian tennis player"},{"monogram":"J","name":"Jonathan Davis","year":1971,"line":"American singer-songwriter"},{"monogram":"B","name":"B. K. Misra","year":1953,"line":"Indian neurosurgeon"},{"monogram":"H","name":"Hargus \"Pig\" Robbins","year":1938,"line":"American musician (died 2022)"},{"monogram":"S","name":"Syl Apps","year":1915,"line":"Canadian pole vaulter, ice hockey player, and politician (died 1998)"},{"monogram":"S","name":"Sam Zemurray","year":1877,"line":"Russian-American businessman, founded the Cuyamel Fruit Company (died 1961)"}],"deaths":[{"year":2025,"text":"<b>Claire van Kampen</b>, English director and composer"},{"year":2014,"text":"<b>Michael Botmang</b>, Nigerian politician, 17th Governor of Plateau State"},{"year":2009,"text":"<b>Grigore Vieru</b>, Romanian poet and author"},{"year":1990,"text":"<b>Melanie Appleby</b>, English singer"},{"year":1952,"text":"<b>Curly Howard</b>, American actor"},{"year":1677,"text":"<b>Jan van Riebeeck</b>, Dutch politician, founded Cape Town"}],"observances":[{"text":"<b>Christian feast day: Amy Carmichael (Church of England)</b>"},{"text":"<b>Christian feast day: Athanasius of Alexandria (Eastern Orthodox Church)</b>"},{"text":"<b>Christian feast day: Confession of Peter (Eastern Orthodox, some Anglican and Lutheran Churches)</b>"},{"text":"<b>Christian feast day: Deicolus</b>"},{"text":"<b>Christian feast day: Margaret of Hungary</b>"},{"text":"<b>Christian feast day: Prisca</b>"},{"text":"<b>Christian feast day: Blessed Regina Protmann</b>"},{"text":"<b>Christian feast day: Volusianus of Tours</b>"}]}